azkar_api_client/__init__.py
azkar_api_client/client.py
azkar_api_client-0.1.0.dist-info/METADATA
azkar_api_client-0.1.0.dist-info/WHEEL
azkar_api_client-0.1.0.dist-info/top_level.txt
azkar_api_client-0.1.0.dist-info/RECORD
