Metadata-Version: 2.4
Name: azkar-api-client
Version: 0.1.0
Summary: مكتبة بايثون لجلب الأذكار من API محدد، مفيدة لتطبيقات إسلامية.
Home-page: https://github.com/yourusername/azkar-api-client
Author: Your Name
Author-email: your.email@example.com
License: MIT
Classifier: Programming Language :: Python :: 3
Classifier: License :: OSI Approved :: MIT License
Classifier: Operating System :: OS Independent
Requires-Python: >=3.6
Requires-Dist: requests
Dynamic: author
Dynamic: author-email
Dynamic: classifier
Dynamic: home-page
Dynamic: license
Dynamic: requires-dist
Dynamic: requires-python
Dynamic: summary
